inkex/__init__.py
inkex/base.py
inkex/bezier.py
inkex/colors.py
inkex/command.py
inkex/css/__init__.py
inkex/css/compiler.py
inkex/css/parser.py
inkex/deprecated/__init__.py
inkex/deprecated/deprecatedeffect.py
inkex/deprecated/main.py
inkex/deprecated/meta.py
inkex/deprecated-simple/README.rst
inkex/deprecated-simple/bezmisc.py
inkex/deprecated-simple/cspsubdiv.py
inkex/deprecated-simple/cubicsuperpath.py
inkex/deprecated-simple/ffgeom.py
inkex/deprecated-simple/run_command.py
inkex/deprecated-simple/simplepath.py
inkex/deprecated-simple/simplestyle.py
inkex/deprecated-simple/simpletransform.py
inkex/elements/__init__.py
inkex/elements/_base.py
inkex/elements/_filters.py
inkex/elements/_groups.py
inkex/elements/_image.py
inkex/elements/_meta.py
inkex/elements/_parser.py
inkex/elements/_polygons.py
inkex/elements/_selected.py
inkex/elements/_svg.py
inkex/elements/_text.py
inkex/elements/_use.py
inkex/elements/_utils.py
inkex/extensions.py
inkex/gui/README.md
inkex/gui/__init__.py
inkex/gui/app.py
inkex/gui/asyncme.py
inkex/gui/listview.py
inkex/gui/pixmap.py
inkex/gui/tester.py
inkex/gui/window.py
inkex/interfaces/IElement.py
inkex/interfaces/__init__.py
inkex/inx.py
inkex/localization.py
inkex/paths/__init__.py
inkex/paths/arc.py
inkex/paths/curves.py
inkex/paths/interfaces.py
inkex/paths/lines.py
inkex/paths/path.py
inkex/paths/quadratic.py
inkex/ports.py
inkex/properties.py
inkex/styles.py
inkex/tester/__init__.py
inkex/tester/decorators.py
inkex/tester/filters.py
inkex/tester/inkscape.extension.rng
inkex/tester/inkscape.extension.schema
inkex/tester/inx.py
inkex/tester/mock.py
inkex/tester/svg.py
inkex/tester/test_inx_file.py
inkex/tester/word.py
inkex/tester/xmldiff.py
inkex/transforms.py
inkex/turtle.py
inkex/tween.py
inkex/units.py
inkex/utils.py
inkex-1.4.0.dist-info/LICENSE.txt
inkex-1.4.0.dist-info/METADATA
inkex-1.4.0.dist-info/WHEEL
inkex-1.4.0.dist-info/RECORD
