Metadata-Version: 2.1
Name: inkex
Version: 1.4.0
Summary: Python extensions for Inkscape core, separated out from main repository.
Home-page: https://gitlab.com/inkscape/extensions
License: GPL-2.0-or-later
Keywords: extensions,graphics,inkscape,svg,vector
Author: Inkscape Authors
Author-email: inkscape-devel@lists.inkscape.org
Maintainer: Martin Owens
Maintainer-email: doctormo@geek-2.com
Requires-Python: >=3.8,<4.0
Classifier: Development Status :: 6 - Mature
Classifier: Intended Audience :: Developers
Classifier: License :: OSI Approved :: GNU General Public License v2 or later (GPLv2+)
Classifier: Programming Language :: Python :: 3
Classifier: Programming Language :: Python :: 3.8
Classifier: Programming Language :: Python :: 3.9
Classifier: Programming Language :: Python :: 3.10
Classifier: Programming Language :: Python :: 3.11
Classifier: Programming Language :: Python :: 3.12
Classifier: Topic :: Multimedia :: Graphics :: Editors :: Vector-Based
Classifier: Topic :: Software Development :: Libraries :: Python Modules
Requires-Dist: Pillow (>=7.0.0)
Requires-Dist: PyGObject (>=3.36) ; platform_system != "Windows"
Requires-Dist: cssselect (>=1.2.0,<2.0.0)
Requires-Dist: lxml (>=4.5.0,<6.0.0)
Requires-Dist: numpy (>=1.17.0,<2.0.0) ; python_version >= "3.7" and python_version < "3.10"
Requires-Dist: numpy (>=1.21.2,<2.0.0) ; python_version >= "3.10" and python_version < "4.0"
Requires-Dist: packaging (>=20.3)
Requires-Dist: pySerial (>=3.4,<4.0)
Requires-Dist: pyparsing (>=3.0.9)
Requires-Dist: scour (>=0.37,<0.38)
Requires-Dist: tinycss2 (>=1.0.1,<2.0.0)
Project-URL: Repository, https://gitlab.com/inkscape/extensions
